template_uuid/__init__.py
template_uuid/apps.py
template_uuid/templatetags/__init__.py
template_uuid/templatetags/template_uuid.py
django_template_uuid-0.0.1.dist-info/LICENSE
django_template_uuid-0.0.1.dist-info/METADATA
django_template_uuid-0.0.1.dist-info/WHEEL
django_template_uuid-0.0.1.dist-info/top_level.txt
django_template_uuid-0.0.1.dist-info/zip-safe
django_template_uuid-0.0.1.dist-info/RECORD
