Metadata-Version: 2.1
Name: django-template-uuid
Version: 0.0.1
Summary: Generate UUIDs for Django templates
Home-page: https://github.com/mpasternak/django-template-uuid
Author: Michał Pasternak
Author-email: michal.dtz@gmail.com
License: MIT license
Platform: UNKNOWN
Classifier: Development Status :: 2 - Pre-Alpha
Classifier: Intended Audience :: Developers
Classifier: License :: OSI Approved :: MIT License
Classifier: Natural Language :: English
Classifier: Programming Language :: Python :: 3
Requires-Dist: django
